uvpy/__init__.py
uvpy/__main__.py
uvpy/app_runner.py
uvpy/cli.py
uvpy/imports.py
uvpy/sandbox.py
uvpy/venv.py
uvpy-0.1.1.dist-info/METADATA
uvpy-0.1.1.dist-info/WHEEL
uvpy-0.1.1.dist-info/entry_points.txt
uvpy-0.1.1.dist-info/licenses/LICENSE
uvpy-0.1.1.dist-info/RECORD
