Metadata-Version: 2.4
Name: uvpy
Version: 0.1.1
Summary: Portable Python App Framework with isolated venvs via uv
Project-URL: Homepage, https://github.com/lepy/uvpy
Project-URL: Repository, https://github.com/lepy/uvpy
Project-URL: Issues, https://github.com/lepy/uvpy/issues
Author: uvpy contributors
License-Expression: MIT
License-File: LICENSE
Keywords: cli,framework,offline,portable,sandbox,uv,venv
Classifier: Development Status :: 4 - Beta
Classifier: Environment :: Console
Classifier: Intended Audience :: Developers
Classifier: License :: OSI Approved :: MIT License
Classifier: Operating System :: OS Independent
Classifier: Programming Language :: Python :: 3
Classifier: Programming Language :: Python :: 3.10
Classifier: Programming Language :: Python :: 3.11
Classifier: Programming Language :: Python :: 3.12
Classifier: Programming Language :: Python :: 3.13
Classifier: Topic :: Software Development :: Libraries :: Application Frameworks
Classifier: Topic :: System :: Software Distribution
Requires-Python: >=3.10
Provides-Extra: dev
Requires-Dist: pytest-cov>=4.0; extra == 'dev'
Requires-Dist: pytest>=7.0; extra == 'dev'
